CHANGES.rst
LICENSE.txt
MANIFEST.in
README.rst
setup.py
cpmoptimize/__init__.py
cpmoptimize/hook.py
cpmoptimize/matcode.py
cpmoptimize/matrices.py
cpmoptimize/recompiler.py
cpmoptimize/run.py
cpmoptimize.egg-info/PKG-INFO
cpmoptimize.egg-info/SOURCES.txt
cpmoptimize.egg-info/dependency_links.txt
cpmoptimize.egg-info/requires.txt
cpmoptimize.egg-info/top_level.txt