Metadata-Version: 1.1
Name: cpmoptimize
Version: 0.4
Summary: A decorator for automatic algorithms optimization via fast matrix exponentiation
Home-page: http://github.com/borzunov/cpmoptimize
Author: Alexander Borzunov
Author-email: borzunov.alexander@gmail.com
License: MIT
Keywords: optimize,matrix,bytecode
Platform: UNKNOWN
Classifier: Development Status :: 4 - Beta
Classifier: Programming Language :: Python
Classifier: Programming Language :: Python :: 2.6
Classifier: Programming Language :: Python :: 2.7
Classifier: Programming Language :: Python :: Implementation :: CPython
Classifier: Programming Language :: Python :: Implementation :: PyPy
Classifier: Intended Audience :: Developers
Classifier: License :: OSI Approved :: MIT License
Classifier: Operating System :: OS Independent
Classifier: Topic :: Software Development :: Libraries :: Python Modules
